supplement_advisor_client/__init__.py
supplement_advisor_client/client.py
supplement_advisor_client/errors.py
supplement_advisor_client-0.1.2.dist-info/METADATA
supplement_advisor_client-0.1.2.dist-info/WHEEL
supplement_advisor_client-0.1.2.dist-info/top_level.txt
supplement_advisor_client-0.1.2.dist-info/RECORD
