Metadata-Version: 2.4
Name: supplement-advisor-client
Version: 0.1.2
Summary: Python client library for Supplement Advisor API
Author-email: Supplement Advisor Team <supplementadvisorclient@gmail.com>
License: MIT
Keywords: supplement,health,api,client,nutrition
Classifier: Development Status :: 3 - Alpha
Classifier: Intended Audience :: Developers
Classifier: Intended Audience :: Healthcare Industry
Classifier: Programming Language :: Python :: 3
Classifier: Programming Language :: Python :: 3.8
Classifier: Programming Language :: Python :: 3.9
Classifier: Programming Language :: Python :: 3.10
Classifier: Programming Language :: Python :: 3.11
Classifier: Programming Language :: Python :: 3.12
Classifier: Topic :: Software Development :: Libraries :: Python Modules
Classifier: Topic :: Scientific/Engineering :: Medical Science Apps.
Requires-Python: >=3.8
Requires-Dist: requests>=2.31.0
